aioface/__init__.py
aioface/bot.py
aioface/config.py
aioface/dispatcher/__init__.py
aioface/dispatcher/dispatcher.py
aioface/dispatcher/utils.py
aioface/fb/__init__.py
aioface/fb/facebook_request.py
aioface/fb/factory.py
aioface/fb/types.py
aioface/fb/utils.py
aioface/storages/__init__.py
aioface/storages/base_storage.py
aioface/storages/fsm/__init__.py
aioface/storages/fsm/fsm.py
aioface/storages/fsm/states.py
aioface/storages/fsm/types.py
aioface-0.0.2.dist-info/LICENSE
aioface-0.0.2.dist-info/METADATA
aioface-0.0.2.dist-info/WHEEL
aioface-0.0.2.dist-info/top_level.txt
aioface-0.0.2.dist-info/RECORD
